[
  {
    "id": "repair_kit_small",
    "name": "リペアキット小",
    "category": "recovery",
    "effect": "hp_restore",
    "value": 30,
    "appearsFrom": 1,
    "shopPrice": 50,
    "dropWeight": 12,
    "description": "マシンHPを30回復する。最も基本的な修理キット。"
  },
  {
    "id": "repair_kit_medium",
    "name": "リペアキット中",
    "category": "recovery",
    "effect": "hp_restore",
    "value": 80,
    "appearsFrom": 5,
    "shopPrice": 120,
    "dropWeight": 9,
    "description": "マシンHPを80回復する。中盤以降の標準的な修理キット。"
  },
  {
    "id": "repair_kit_large",
    "name": "リペアキット大",
    "category": "recovery",
    "effect": "hp_restore",
    "value": 200,
    "appearsFrom": 12,
    "shopPrice": 280,
    "dropWeight": 5,
    "description": "マシンHPを200回復する。深層探索に欠かせない大型キット。"
  },
  {
    "id": "full_repair_kit",
    "name": "フルリペアキット",
    "category": "recovery",
    "effect": "hp_restore_full",
    "value": 9999,
    "appearsFrom": 20,
    "shopPrice": 800,
    "dropWeight": 2,
    "description": "マシンHPを全回復する。希少だが緊急時に非常に有効。"
  },
  {
    "id": "energy_pack",
    "name": "エネルギーパック",
    "category": "recovery",
    "effect": "energy_restore",
    "value": 50,
    "appearsFrom": 3,
    "shopPrice": 80,
    "dropWeight": 10,
    "description": "エネルギーを50回復する。特殊武器や道具の使用に必要。"
  },
  {
    "id": "energy_pack_large",
    "name": "エネルギーパック大",
    "category": "recovery",
    "effect": "energy_restore",
    "value": 100,
    "appearsFrom": 12,
    "shopPrice": 180,
    "dropWeight": 5,
    "description": "エネルギーを100回復する。特殊武器を多用する戦術での必需品。"
  },
  {
    "id": "weapon_repair_kit",
    "name": "修理キット",
    "category": "weapon",
    "effect": "weapon_durability_restore_full",
    "value": 1,
    "appearsFrom": 5,
    "shopPrice": 100,
    "dropWeight": 8,
    "description": "武器1つの耐久度を最大値まで完全回復する。"
  },
  {
    "id": "upgrade_core_i",
    "name": "強化コアI",
    "category": "weapon",
    "effect": "weapon_upgrade_material",
    "tier": 1,
    "value": 1,
    "appearsFrom": 3,
    "shopPrice": 200,
    "dropWeight": 7,
    "description": "武器Lv1→2のアップグレードに使用する強化素材。3個必要。"
  },
  {
    "id": "upgrade_core_ii",
    "name": "強化コアII",
    "category": "weapon",
    "effect": "weapon_upgrade_material",
    "tier": 2,
    "value": 1,
    "appearsFrom": 8,
    "shopPrice": 500,
    "dropWeight": 4,
    "description": "武器Lv2→3のアップグレードに使用する強化素材。3個必要。"
  },
  {
    "id": "upgrade_core_iii",
    "name": "強化コアIII",
    "category": "weapon",
    "effect": "weapon_upgrade_material",
    "tier": 3,
    "value": 1,
    "appearsFrom": 18,
    "shopPrice": 1200,
    "dropWeight": 2,
    "description": "武器Lv3→4、Lv4→5のアップグレードに使用する上位素材。それぞれ5個・10個必要。"
  },
  {
    "id": "floor_map",
    "name": "フロアマップ",
    "category": "exploration",
    "effect": "reveal_floor",
    "value": 1,
    "appearsFrom": 3,
    "shopPrice": 150,
    "dropWeight": 7,
    "description": "そのフロアの地形を全て明らかにする。敵の位置は表示されない。"
  },
  {
    "id": "enemy_radar_map",
    "name": "敵探知マップ",
    "category": "exploration",
    "effect": "reveal_enemies",
    "value": 1,
    "appearsFrom": 8,
    "shopPrice": 250,
    "dropWeight": 5,
    "description": "そのフロアの全敵の位置を明らかにする。地形は表示されない。"
  },
  {
    "id": "smoke_bomb",
    "name": "煙幕弾",
    "category": "combat",
    "effect": "enemy_lose_tracking",
    "value": 3,
    "appearsFrom": 2,
    "shopPrice": 70,
    "dropWeight": 9,
    "description": "3ターンの間、敵がプレイヤーを追跡できなくなる。ボス戦での緊急回避にも有効。"
  },
  {
    "id": "emp_grenade",
    "name": "EMPグレネード",
    "category": "combat",
    "effect": "stun_area",
    "value": 3,
    "radius": 1,
    "appearsFrom": 12,
    "shopPrice": 300,
    "dropWeight": 4,
    "description": "投擲地点の3×3範囲内の全敵を3ターン行動不能にする。"
  },
  {
    "id": "flash_grenade",
    "name": "フラッシュグレネード",
    "category": "combat",
    "effect": "stun_radius_2",
    "value": 2,
    "radius": 2,
    "appearsFrom": 5,
    "shopPrice": 150,
    "dropWeight": 7,
    "description": "強烈な閃光で周囲2タイルの敵を2ターン行動不能にする。序盤から使える範囲スタン手段。"
  },
  {
    "id": "speed_boost",
    "name": "加速ブースト",
    "category": "combat",
    "effect": "speed_up",
    "value": 2,
    "duration": 5,
    "appearsFrom": 4,
    "shopPrice": 100,
    "dropWeight": 6,
    "description": "5ターンの間、移動速度が+2される。逃走や先制攻撃に活用できる。"
  },
  {
    "id": "barrier_capsule",
    "name": "バリアカプセル",
    "category": "combat",
    "effect": "damage_nullify",
    "value": 3,
    "appearsFrom": 10,
    "shopPrice": 350,
    "dropWeight": 4,
    "description": "次の3回のダメージを無効化するバリアを展開する。"
  },
  {
    "id": "holy_oil",
    "name": "聖なるオイル",
    "category": "combat",
    "effect": "boss_damage_up",
    "value": 1.5,
    "duration": 5,
    "appearsFrom": 8,
    "shopPrice": 500,
    "dropWeight": 3,
    "description": "5ターンの間、ボスへのダメージを+50%にする。ボス戦の切り札。"
  },
  {
    "id": "escape_module",
    "name": "エスケープモジュール",
    "category": "special",
    "effect": "return_to_start",
    "value": 1,
    "appearsFrom": 5,
    "shopPrice": 400,
    "dropWeight": 3,
    "description": "即座にスタート地点へ帰還する。所持品は全て保持される。ラスボス戦では使用不可。"
  },
  {
    "id": "teleport_beacon",
    "name": "テレポートビーコン",
    "category": "special",
    "effect": "set_warp_point",
    "value": 1,
    "appearsFrom": 7,
    "shopPrice": 200,
    "dropWeight": 5,
    "description": "設置した地点にいつでも瞬間移動できるビーコンを設置する（1フロア限定）。"
  },
  {
    "id": "decoy_drone",
    "name": "デコイドローン",
    "category": "special",
    "effect": "decoy",
    "value": 5,
    "duration": 5,
    "appearsFrom": 8,
    "shopPrice": 180,
    "dropWeight": 5,
    "description": "5ターンの間、敵の注意をドローンに引きつける。強敵から逃げる際に有効。"
  },
  {
    "id": "id_scope",
    "name": "識別スコープ",
    "category": "special",
    "effect": "identify_item",
    "value": 1,
    "appearsFrom": 1,
    "shopPrice": 60,
    "dropWeight": 10,
    "description": "未鑑定アイテムを鑑定して正体を明らかにする。ハズレアイテムを掴まされるリスクを回避できる。"
  },
  {
    "id": "armor_plate_i",
    "name": "装甲プレートI",
    "category": "machine_upgrade",
    "effect": "armor_up",
    "value": 5,
    "appearsFrom": 1,
    "shopPrice": 300,
    "dropWeight": 6,
    "description": "マシンの装甲値を永続的に+5する強化パーツ。"
  },
  {
    "id": "armor_plate_ii",
    "name": "装甲プレートII",
    "category": "machine_upgrade",
    "effect": "armor_up",
    "value": 15,
    "appearsFrom": 10,
    "shopPrice": 800,
    "dropWeight": 4,
    "description": "マシンの装甲値を永続的に+15する強化パーツ。"
  },
  {
    "id": "armor_plate_iii",
    "name": "装甲プレートIII",
    "category": "machine_upgrade",
    "effect": "armor_up",
    "value": 40,
    "appearsFrom": 25,
    "shopPrice": 2500,
    "dropWeight": 2,
    "description": "マシンの装甲値を永続的に+40する上位強化パーツ。"
  },
  {
    "id": "boost_engine_i",
    "name": "ブーストエンジンI",
    "category": "machine_upgrade",
    "effect": "speed_up_permanent",
    "value": 1,
    "appearsFrom": 5,
    "shopPrice": 600,
    "dropWeight": 3,
    "description": "マシンの移動速度を永続的に+1する強化パーツ。"
  },
  {
    "id": "boost_engine_ii",
    "name": "ブーストエンジンII",
    "category": "machine_upgrade",
    "effect": "speed_up_permanent",
    "value": 1,
    "appearsFrom": 20,
    "shopPrice": 2000,
    "dropWeight": 2,
    "description": "マシンの移動速度を永続的に+1する上位強化パーツ。"
  },
  {
    "id": "weapon_rack_expansion",
    "name": "拡張ウェポンラック",
    "category": "machine_upgrade",
    "effect": "weapon_slot_up",
    "value": 1,
    "appearsFrom": 8,
    "shopPrice": 1500,
    "dropWeight": 2,
    "description": "武器スロットを永続的に+1する拡張パーツ。"
  },
  {
    "id": "tool_bay_expansion",
    "name": "拡張ツールベイ",
    "category": "machine_upgrade",
    "effect": "tool_slot_up",
    "value": 1,
    "appearsFrom": 8,
    "shopPrice": 1500,
    "dropWeight": 2,
    "description": "道具スロットを永続的に+1する拡張パーツ。"
  },
  {
    "id": "cargo_expansion",
    "name": "カーゴ拡張",
    "category": "machine_upgrade",
    "effect": "pouch_capacity_up",
    "value": 5,
    "appearsFrom": 3,
    "shopPrice": 400,
    "dropWeight": 4,
    "description": "アイテムポーチの容量を永続的に+5する拡張パーツ。"
  },
  {
    "id": "reactor_upgrade",
    "name": "リアクター強化",
    "category": "machine_upgrade",
    "effect": "energy_max_up",
    "value": 50,
    "appearsFrom": 5,
    "shopPrice": 700,
    "dropWeight": 3,
    "description": "エネルギーの最大値を永続的に+50する強化パーツ。"
  },
  {
    "id": "frame_upgrade_i",
    "name": "フレーム強化I",
    "category": "machine_upgrade",
    "effect": "max_hp_up",
    "value": 30,
    "appearsFrom": 1,
    "shopPrice": 350,
    "dropWeight": 6,
    "description": "マシンHPの最大値を永続的に+30する強化パーツ。"
  },
  {
    "id": "frame_upgrade_ii",
    "name": "フレーム強化II",
    "category": "machine_upgrade",
    "effect": "max_hp_up",
    "value": 80,
    "appearsFrom": 10,
    "shopPrice": 1000,
    "dropWeight": 3,
    "description": "マシンHPの最大値を永続的に+80する強化パーツ。"
  },
  {
    "id": "frame_upgrade_iii",
    "name": "フレーム強化III",
    "category": "machine_upgrade",
    "effect": "max_hp_up",
    "value": 200,
    "appearsFrom": 25,
    "shopPrice": 3000,
    "dropWeight": 1,
    "description": "マシンHPの最大値を永続的に+200する上位強化パーツ。"
  },
  {
    "id": "warehouse_ticket",
    "name": "倉庫拡張チケット",
    "category": "special",
    "effect": "warehouse_expansion",
    "value": 1,
    "appearsFrom": 5,
    "shopPrice": 1000,
    "dropWeight": 2,
    "description": "倉庫の拡張に使用するチケット。ゴールドと一緒に倉庫管理人に渡す。"
  },
  {
    "id": "unknown_part_a",
    "name": "???のパーツ（A型）",
    "category": "unidentified",
    "effect": "unknown",
    "value": 1,
    "appearsFrom": 5,
    "shopPrice": 0,
    "dropWeight": 6,
    "revealItems": ["repair_kit_medium", "energy_pack", "upgrade_core_i", "armor_plate_i", "smoke_bomb", "weapon_repair_kit"],
    "description": "未鑑定の不明パーツ。識別スコープで正体を明かせる。良いものもハズレもある。"
  },
  {
    "id": "unknown_part_b",
    "name": "???のパーツ（B型）",
    "category": "unidentified",
    "effect": "unknown",
    "value": 1,
    "appearsFrom": 10,
    "shopPrice": 0,
    "dropWeight": 4,
    "revealItems": ["repair_kit_large", "energy_pack_large", "upgrade_core_ii", "repair_kit_medium", "barrier_capsule", "armor_plate_ii"],
    "description": "未鑑定の上位不明パーツ。識別スコープで正体を明かせる。深層ほど高価値な可能性がある。"
  },
  {
    "id": "scrap_metal_i",
    "name": "廃金属I",
    "category": "material",
    "effect": "sell_only",
    "value": 20,
    "appearsFrom": 1,
    "shopPrice": 0,
    "sellPrice": 20,
    "dropWeight": 10,
    "description": "初期階層で入手できる廃材。ショップで売ってゴールドにする。"
  },
  {
    "id": "scrap_metal_ii",
    "name": "廃金属II",
    "category": "material",
    "effect": "sell_only",
    "value": 50,
    "appearsFrom": 8,
    "shopPrice": 0,
    "sellPrice": 50,
    "dropWeight": 8,
    "description": "中層階の廃材。より高品質で高く売れる。"
  },
  {
    "id": "scrap_metal_iii",
    "name": "廃金属III",
    "category": "material",
    "effect": "sell_only",
    "value": 100,
    "appearsFrom": 16,
    "shopPrice": 0,
    "sellPrice": 100,
    "dropWeight": 6,
    "description": "深層の廃材。希少で高価値。"
  },
  {
    "id": "rare_circuit",
    "name": "希少回路",
    "category": "material",
    "effect": "sell_only",
    "value": 150,
    "appearsFrom": 10,
    "shopPrice": 0,
    "sellPrice": 150,
    "dropWeight": 4,
    "description": "売却専用の希少素材。高値がつく。"
  }
]
